{
  "id": "2026-04-05-doctors-seek-implementation-of-next-for-mbbs-students",
  "issueKey": "2026-04-05",
  "segment": "pharma",
  "title": "Doctors seek implementation of NExT for MBBS students",
  "summary": "In an editorial published last month in the Journal of Family Medicine and Primary Care, titled \"Immediate NExT rollout is vital for MBBS students and the medical education ecosystem of India\", the doctors said current undergraduate medical assessments are...",
  "source": "ET Healthworld",
  "sourceHost": "health.economictimes.indiatimes.com",
  "region": "India",
  "country": "India",
  "publishedAt": "2026-04-05T07:17:24.000Z",
  "publishedLabel": "April 5, 2026",
  "category": "Industry Update",
  "image": "https://etimg.etb2bimg.com/thumb/msid-130035044,imgsize-116096,width-1200,height=627,overlay-ethealth,resizemode-75/education/doctors-seek-implementation-of-next-for-mbbs-students.jpg",
  "thbAction": "Position THB's pharma CRM and omnichannel HCP engagement workflows to support launch planning, KAM orchestration, and compliant follow-up across India and the Middle East.",
  "justIn": true,
  "originalUrl": "https://health.economictimes.indiatimes.com/news/education/doctors-seek-implementation-of-next-for-mbbs-students/130035044",
  "canonicalUrl": "https://health.economictimes.indiatimes.com/news/education/doctors-seek-implementation-of-next-for-mbbs-students/130035044",
  "contentHtml": "\n        \n                <ul>\n                    \n                     <li><a href=\"/news/education\" target=\"_blank\" rel=\"noopener noreferrer\">Education</a></li>                     <li>4 min read</li>                 </ul>\n                            \n        \n                                    \n                                                                                    <ul>\n                                                                                                                                                    <li><a href=\"/agency/87654375/PTI\" target=\"_blank\" rel=\"noopener noreferrer\">PTI</a></li>\n                                                                                            </ul>\n                                                                                <ul>\n                                                                                            <li>Published On Apr 5, 2026 at 12:47 PM IST</li>\n                                                                                                                                </ul>\n                                    \n                                \n\n                    <!-- Display video article in news article for the custom next story -->\n                    \n                    <!-- Modifying the body placing embeds,promoslots,related etc.-->\n                                        <figure><img src=\"/images/default.jpg\" alt=\"\"></figure>New Delhi: Members of the Resident Doctors Association and the Student Association of <a href=\"/tag/aiims+delhi\" target=\"_blank\" rel=\"noopener noreferrer\">AIIMS Delhi</a>, along with faculty from <a href=\"/tag/aiims+delhi\" target=\"_blank\" rel=\"noopener noreferrer\">AIIMS Delhi</a>, Nagpur, Patna and RML, have sought the implementation of the <a href=\"/tag/national+exit+test\" target=\"_blank\" rel=\"noopener noreferrer\">National Exit Test</a> (NExT) for <a href=\"/tag/mbbs\" target=\"_blank\" rel=\"noopener noreferrer\">MBBS</a> students.They said it addresses shortcomings in existing university and postgraduate entrance examinations and offers a streamlined, competency-based assessment system.<!-- PROMOSLOT_M -->In an editorial published last month in the Journal of Family Medicine and Primary Care, titled \"Immediate NExT rollout is vital for <a href=\"/tag/mbbs\" target=\"_blank\" rel=\"noopener noreferrer\">MBBS</a> students and the medical education ecosystem of India\", the doctors said current undergraduate medical assessments are inconsistent and fragmented.\n                            <p>Advt\n                            </p>\n\n                              \n                                                         \n                        They added that these exams are often poorly aligned with competency-based training. The authors said NExT aims to introduce a uniform, transparent and clinically relevant evaluation framework.<!-- PROMOSLOT_M -->NExT, introduced through the National Medical Commission Act, 2019, and further elaborated in the 2023 Gazette notification, was envisaged as a singular qualifying examination to replace three existing exams in the field of medicine-the final MBBS exams, the National Eligibility-cum-Entrance Test for post-graduate seats (NEET-PG), and the Foreign Medical Graduate Examination (FMGE) for foreign medical graduates to practice medicine in India.<!-- PROMOSLOT_M -->However, the test has been postponed multiple times, creating uncertainty and delaying reforms, the authors said.The editorial explains why immediate implementation is essential.It said NExT can improve the validity and reliability of assessments, support student learning, and increase institutional transparency. It also aimed to help build a more competent medical workforce.<!-- PROMOSLOT_M -->The authors noted that university-based MBBS final exams vary widely in quality and fairness. Theory papers are often subjective. Content does not always align with national competencies, and evaluation standards differ across institutions.\n                            <p>Advt\n                            </p>\n\n                              \n                                                         \n                        \"This creates inconsistency in determining whether a graduate is ready to practise medicine,\" they said.They also pointed out that current PG entrance tests rely on a relatively small pool of about 200 Multiple Choice Questions (MCQs) to assess the entire MBBS curriculum.<!-- PROMOSLOT_M -->This limited sampling reduces reliability and increases the role of chance. The focus on recall-based questions also promotes coaching-driven preparation over clinical learning. Currently, students must prepare for two very different exams.The university final exam is theory-heavy and long-answer-based, while the PG entrance test is entirely MCQ-based.\n                            <p>Advt\n                            </p>\n\n                              \n                                                         \n                        \"This mismatch forces students to adopt different strategies and adds to stress,\" the authors said.The NExT aims to unify both into a single standardised exam.\"A national exit examination is not just a format change. It is a shift towards clinically oriented assessment with a larger and uniform question pool,\" they said.This, they added, will improve learning outcomes and raise standards.The authors said NExT Step 1 includes a larger MCQ pool based on clinical vignettes and applied reasoning.This reflects real-life decision-making. NExT Step 2 aims to assess practical skills, communication and clinical competence through structured clinical exams, though details are still awaited.<!-- PROMOSLOT -->They added that NExT applies to all students, including those from government and private colleges, as well as foreign medical graduates.\"By assessing all candidates through the same national standard, it strengthens public confidence in medical training and ensures that every licensed doctor demonstrates a uniform threshold of competence, regardless of where they received their education,\" the authors said.The editorial said a unified test will reduce the burden of preparing for multiple exams with different formats. The NExT Step 1 scores may be used not only for postgraduate admissions but also for government service positions, and various fellowships or scholarship opportunities. A single score, it said, will improve transparency and reduce arbitrary selection processes.The editorial highlighted that a uniform national benchmark will allow colleges, especially new and private institutions, to demonstrate their training quality through measurable student outcomes.\"Experiences from engineering, management, and dental education over the past two decades illustrate how rapid expansion without strong evaluation mechanisms can compromise quality. Many institutions in these sectors lacked rigorous student assessment processes and gradually became degree-granting centres rather than fostering meaningful learning. The closure of several such colleges highlights the long-term risks associated with expansion in the absence of credible quality assurance,\" the editorial stated.\"In medicine, poor training can lead to serious harm. NExT will set a national minimum standard that every graduate must achieve before independent practice, thereby protecting public health and ensuring trust in the profession,\" the editorial stressed.To ensure a smooth rollout, the authors recommended preparatory support, including multiple mock tests, sample questions, workbooks, and detailed syllabus material.                    \n                                                                    \n                                                                \n                                <ul>\n                                    \n\n                                                                        <li><a href=\"/agency/87654375/PTI\" target=\"_blank\" rel=\"noopener noreferrer\">PTI</a></li>\n                                </ul>\n                                <ul>\n                                    <!-- <li> Updated On Apr 5, 2026 at 12:47 PM IST</li> -->\n                                    <li>Published On Apr 5, 2026 at 12:47 PM IST</li>\n                                    <!-- <li class=\"desktop-view\">4 min read</li> -->\n                                </ul>\n                            \n                                        \n\n                    \n\n                    <!-- Comment Section -->\n                    \n                    <!-- Comment Section -->\n\n                    \n                      \n    \n            <p>\n                </p><h2>Join the community of 2M+ industry professionals. </h2>   \n                <h3>Subscribe to Newsletter to get latest insights &amp; analysis in your inbox.</h3>\n            <p></p>\n\n            <!-- <figure class=\"top-newsletter-subs__icon-nl\" role=\"presentation\" aria-label=\"Newsletter icon\">\n                <img loading=\"lazy\" src=\"https://st.etb2bimg.com/Themes/Release/theme4/images/icons/icon-newsletter.svg\" alt=\"Newsletter icon\" width=\"55\" height=\"55\">\n            </figure> -->\n        \n            \n                \n                    <h2>All about ETHealthworld industry right on your smartphone! </h2>\n                    <ul>\n                        <li><a href=\"/app\" target=\"_blank\" rel=\"noopener noreferrer\">Download the ETHealthworld App</a> and get the Realtime updates and Save your favourite articles.</li>\n                    </ul>\n                                            <!-- <div class=\"app-store-container desktop-view\">\n                            <a href=\"/app\" title=\"\" aria-label=\"Play Store\">\n                                <img loading=\"lazy\" width=\"20\" height=\"20\" src=\"https://st.etb2bimg.com/Themes/Release/theme4/images/icons/icon-g-play.png\" alt=\"\" />\n                            </a>\n                            <a href=\"/app\" title=\"App Store\">\n                                <img loading=\"lazy\" width=\"20\" height=\"20\" src=\"https://st.etb2bimg.com/Themes/Release/theme4/images/icons/icon-app-store.png\" alt=\"\" />\n                            </a>\n                        </div>    -->\n                         \n                \n                                    <figure>\n                        <!-- <i></i>\n                        <span class=\"scan-text\">Scan to download App</span> -->\n                        <img src=\"https://st.etb2bimg.com/Themes/Release/theme4/images/bar-codes/health_barcode.png?mod=3225\" alt=\"\">                        \n                        <!-- <span class=\"border-bottom\"></span> -->\n                    </figure>\n                            \n       \n\n\n                    \n                \n            \n    <!-- Category Most Read Placement -->"
}
