{
  "id": "2026-04-05-pgi-revamps-procurement-after-ayushman-bharat-scam",
  "issueKey": "2026-04-05",
  "segment": "providers",
  "title": "PGI revamps procurement after Ayushman Bharat scam",
  "summary": "The Ayushman scam involved the transfer of around Rs 88 lakh to pharmaceutical vendors without valid prescriptions. PGI is now transitioning to a secure online indenting system.",
  "source": "ET Healthworld Hospitals",
  "sourceHost": "health.economictimes.indiatimes.com",
  "region": "India",
  "country": "India",
  "publishedAt": "2026-04-05T07:26:08.000Z",
  "publishedLabel": "April 5, 2026",
  "category": "Provider Update",
  "image": "https://etimg.etb2bimg.com/thumb/msid-130035189,imgsize-271294,width-1200,height=627,overlay-ethealth,resizemode-75/hospitals/pgi-revamps-procurement-after-ayushman-bharat-scam.jpg",
  "thbAction": "Map the news to THB's provider CRM for referral growth, patient lifecycle engagement, and multi-facility relationship management across hospital and provider networks.",
  "justIn": true,
  "originalUrl": "https://health.economictimes.indiatimes.com/news/hospitals/pgi-revamps-procurement-after-ayushman-bharat-scam/130035189",
  "canonicalUrl": "https://health.economictimes.indiatimes.com/news/hospitals/pgi-revamps-procurement-after-ayushman-bharat-scam/130035189",
  "contentHtml": "\n        \n                <ul>\n                    \n                     <li><a href=\"/news/hospitals\" target=\"_blank\" rel=\"noopener noreferrer\">Hospitals</a></li>                     <li>2 min read</li>                 </ul>\n                            \n        \n                                    \n\n                                                                            <p><img src=\"https://health.economictimes.indiatimes.com/Themes/Release/theme4/images/icons/et-default-user.svg\" alt=\"Shimona Kanwar\">\n                                            \n                                        </p>\n                                                                        \n                                                                                    <ul>\n                                                                                                    <li>\n                                                                                                                    <a>Shimona Kanwar</a>\n\n                                                                                                                                                                                                                                        \n                                                                                                            </li>\n                                                                                                                                                    <li><a href=\"/agency/87654367/TNN\" target=\"_blank\" rel=\"noopener noreferrer\">TNN</a></li>\n                                                                                            </ul>\n                                                                                <ul>\n                                                                                            <li>Published On Apr 5, 2026 at 12:56 PM IST</li>\n                                                                                                                                </ul>\n                                    \n                                                                            \n                                                                        \n                                \n                                \n\n                    <!-- Display video article in news article for the custom next story -->\n                    \n                    <!-- Modifying the body placing embeds,promoslots,related etc.-->\n                                        <figure><img src=\"/images/default.jpg\" alt=\"\"></figure> Chandigarh: Following the high-profile <a href=\"/tag/ayushman+bharat+scam\" target=\"_blank\" rel=\"noopener noreferrer\">Ayushman Bharat scam</a>, in which funds were siphoned off through forged bills and deceased patients' records, PGI has overhauled its procurement process. The institute has introduced a \"zero third-party\" policy to eliminate middlemen and prevent future financial irregularities.<figure><img src=\"/images/default.jpg\" alt=\"\"></figure> In a major policy shift, the institute has decided to completely remove third-party vendors from the procurement chain for implants and medical consumables. This move ensures that all transactions for surgeries and specialised treatment under cashless schemes are handled directly between the hospital and authorised manufacturers or internal pharmacies, leaving no room for private intermediaries to interact with the medical staff.<!-- PROMOSLOT_M -->\n                            <p>Advt\n                            </p>\n\n                              \n                                                         \n                        To curb the influence of external agents, the administration has strictly prohibited vendors from dealing directly with doctors, hospital staff, or patients' attendants. Previously, these vendors often acted as facilitators for obtaining implants, which led to price manipulation and billing fraud. All requirements will now be routed through a centralised internal system to maintain transparency.<!-- PROMOSLOT_M -->The Ayushman scam involved the transfer of around Rs 88 lakh to pharmaceutical vendors without valid prescriptions. PGI is now transitioning to a secure online indenting system. This digital solution, integrated with the Hospital Information System, replaces manual records with a real-time tracking mechanism. Every medicine and implant issued under the schemes is digitally linked to a specific patient's ID and the treating consultant's authorisation.<!-- PROMOSLOT_M -->To further safeguard patients from the \"medicine-resale\" racket, the institute is increasing its staffing to ensure direct delivery of medications and implants to the patient's bedside. By eliminating the need for attendants to visit external pharmacies with manual slips, the hospital aims to shut down the use of counterfeit stamps and forged documents that were central to the recent scam.<!-- PROMOSLOT_M -->The Ayushman Bharat scheme is designed to provide eligible families with free medical treatment and medications up to Rs 5 lakh annually. For medicines exceeding Rs 2,000, patients require a doctor's prescription documented in an indent book, which must be verified with stamps from the doctor, nursing officer, Ayushman counter, and dispensary.                    \n                                                                    \n                                                                \n                                <ul>\n                                                                            <!-- <li>By <span>Shimona Kanwar</span>,</li> -->\n                                    \n\n                                                                            <li>By\n                                                                                            <a>Shimona Kanwar</a>\n\n                                                                                                                                                                                        , \n                                                                                    </li>\n                                                                        <li><a href=\"/agency/87654367/TNN\" target=\"_blank\" rel=\"noopener noreferrer\">TNN</a></li>\n                                </ul>\n                                <ul>\n                                    <!-- <li> Updated On Apr 5, 2026 at 12:56 PM IST</li> -->\n                                    <li>Published On Apr 5, 2026 at 12:56 PM IST</li>\n                                    <!-- <li class=\"desktop-view\">2 min read</li> -->\n                                </ul>\n                            \n                                        \n\n                    \n\n                    <!-- Comment Section -->\n                    \n                    <!-- Comment Section -->\n\n                    \n                      \n    \n            <p>\n                </p><h2>Join the community of 2M+ industry professionals. </h2>   \n                <h3>Subscribe to Newsletter to get latest insights &amp; analysis in your inbox.</h3>\n            <p></p>\n\n            <!-- <figure class=\"top-newsletter-subs__icon-nl\" role=\"presentation\" aria-label=\"Newsletter icon\">\n                <img loading=\"lazy\" src=\"https://st.etb2bimg.com/Themes/Release/theme4/images/icons/icon-newsletter.svg\" alt=\"Newsletter icon\" width=\"55\" height=\"55\">\n            </figure> -->\n        \n            \n                \n                    <h2>All about ETHealthworld industry right on your smartphone! </h2>\n                    <ul>\n                        <li><a href=\"/app\" target=\"_blank\" rel=\"noopener noreferrer\">Download the ETHealthworld App</a> and get the Realtime updates and Save your favourite articles.</li>\n                    </ul>\n                                            <!-- <div class=\"app-store-container desktop-view\">\n                            <a href=\"/app\" title=\"\" aria-label=\"Play Store\">\n                                <img loading=\"lazy\" width=\"20\" height=\"20\" src=\"https://st.etb2bimg.com/Themes/Release/theme4/images/icons/icon-g-play.png\" alt=\"\" />\n                            </a>\n                            <a href=\"/app\" title=\"App Store\">\n                                <img loading=\"lazy\" width=\"20\" height=\"20\" src=\"https://st.etb2bimg.com/Themes/Release/theme4/images/icons/icon-app-store.png\" alt=\"\" />\n                            </a>\n                        </div>    -->\n                         \n                \n                                    <figure>\n                        <!-- <i></i>\n                        <span class=\"scan-text\">Scan to download App</span> -->\n                        <img src=\"https://st.etb2bimg.com/Themes/Release/theme4/images/bar-codes/health_barcode.png?mod=3225\" alt=\"\">                        \n                        <!-- <span class=\"border-bottom\"></span> -->\n                    </figure>\n                            \n       \n\n\n                    \n                \n            \n    <!-- Category Most Read Placement -->"
}
