{
  "id": "2026-05-17-six-in-10-patients-drop-off-after-consultation-due-to-financing-delays-s",
  "issueKey": "2026-05-17",
  "segment": "pharma",
  "title": "Six in 10 patients drop-off after consultation due to financing delays: Survey",
  "summary": "The survey highlights that over 52 per cent of clinics experience more than 20 per cent patient drop-offs post consultation when financing is unavailable, while 16 per cent report drop-offs exceeding 40 per cent.",
  "source": "ET Healthworld",
  "sourceHost": "health.economictimes.indiatimes.com",
  "region": "India",
  "country": "India",
  "publishedAt": "2026-05-19T08:07:32.000Z",
  "publishedLabel": "May 19, 2026",
  "category": "Industry Update",
  "image": "https://etimg.etb2bimg.com/thumb/msid-131194683,imgsize-153673,width-1200,height=627,overlay-ethealth,resizemode-75/industry/survey-reveals-financial-hurdles-preventing-60-of-patients-from-receiving-elective-healthcare-in-india.jpg",
  "thbAction": "Position THB's pharma CRM and omnichannel HCP engagement workflows to support launch planning, KAM orchestration, and compliant follow-up across India and the Middle East.",
  "justIn": true,
  "originalUrl": "https://health.economictimes.indiatimes.com/news/industry/survey-reveals-financial-hurdles-preventing-60-of-patients-from-receiving-elective-healthcare-in-india/131194683",
  "canonicalUrl": "https://health.economictimes.indiatimes.com/news/industry/survey-reveals-financial-hurdles-preventing-60-of-patients-from-receiving-elective-healthcare-in-india/131194683",
  "contentHtml": "\n                                    \n\n                                                                            <p><img src=\"https://health.economictimes.indiatimes.com/Themes/Release/theme4/images/icons/et-default-user.svg\" alt=\"Online Bureau\">\n                                            \n                                        </p>\n                                                                        \n                                                                                    <ul>\n                                                                                                    <li>\n                                                                                                                    <a>Online Bureau</a>\n\n                                                                                                                                                                                                                                        \n                                                                                                            </li>\n                                                                                                                                                    <li><a href=\"/agency/88675629/ETHealthWorld\" target=\"_blank\" rel=\"noopener noreferrer\">ETHealthWorld</a></li>\n                                                                                            </ul>\n                                                                                <ul>\n                                                                                            <li>Published On May 19, 2026 at 01:37 PM IST</li>\n                                                                                                                                </ul>\n                                    \n                                                                            \n                                                                        \n                                \n                                \n\n                    <!-- Display video article in news article for the custom next story -->\n                    \n                    <!-- Modifying the body placing embeds,promoslots,related etc.-->\n                                        <figure><img src=\"/images/default.jpg\" alt=\"\"></figure><p>New Delhi: Financial constraints and slow financing approvals are emerging as a major barrier in India’s <a href=\"/tag/elective+healthcare\" target=\"_blank\" rel=\"noopener noreferrer\">elective healthcare</a> sector, with nearly six in 10 patients leaving clinics without treatment after consultation, according to a nationwide survey by <a href=\"/tag/carepay\" target=\"_blank\" rel=\"noopener noreferrer\">CarePay</a>, a fintech platform for healthcare financial inclusion.The survey of 3,100 wellness and elective healthcare clinics found that financial liquidity not lack of patient intent is the biggest reason for treatment drop-offs after consultation. Procedures such as IVF, dermatology, cosmetology, dental and wellness treatments often require upfront payments, with IVF cycles costing around Rs. 1.2 to 1.5 lakh, pushing many patients to seek financing options.</p><!-- PROMOSLOT_M -->\n                            <p>Advt\n                            </p>\n\n                              \n                                                         \n                        <p>Clinics reported that slow approval processes, uncertain financing outcomes, or outright rejection of loans frequently lead patients to abandon treatment plans at the payment stage.According to the study, 41 per cent of premium clinics say most patients now demand no-cost EMI options, and 89 per cent of clinics recommend embedded multi-lender financing systems to improve treatment conversion rates.</p><!-- PROMOSLOT_M --><p>“Patients are not refusing treatment because they cannot pay upfront. Wellness care in India has become aspirational and high-ticket, but household cash flows haven’t kept pace,” said Gaurav Gupta, Co-Founder and CEO, CarePay.</p><p>The survey highlights that over 52 per cent of clinics experience more than 20 per cent <a href=\"/tag/patient+drop-offs\" target=\"_blank\" rel=\"noopener noreferrer\">patient drop-offs</a> post consultation when financing is unavailable, while 16 per cent report drop-offs exceeding 40 per cent. </p><!-- PROMOSLOT_M --><p>Clinics using <a href=\"/tag/embedded+financing+solutions\" target=\"_blank\" rel=\"noopener noreferrer\">embedded financing solutions</a> reported faster treatment decisions (51 per cent ), fewer drop-offs (30 per cent ), and higher treatment value (19 per cent). The ability to check financing eligibility within 30 seconds was cited as a key factor in maintaining patient momentum after consultations.India’s wellness and elective healthcare market, estimated at over $50 billion in 2025 and projected to reach $100 billion by 2030, remains largely out-of-pocket and credit-underserved, making financing infrastructure increasingly critical for clinics seeking to convert consultations into treatments.                    </p><!-- Category Most Read Placement -->\n                                                                    \n                                                                \n                                <ul>\n                                                                            <!-- <li>By <span>Online Bureau</span>,</li> -->\n                                    \n\n                                                                            <li>By\n                                                                                            <a>Online Bureau</a>\n\n                                                                                                                                                                                        , \n                                                                                    </li>\n                                                                        <li><a href=\"/agency/88675629/ETHealthWorld\" target=\"_blank\" rel=\"noopener noreferrer\">ETHealthWorld</a></li>\n                                </ul>\n                                <ul>\n                                    <!-- <li> Updated On May 19, 2026 at 01:37 PM IST</li> -->\n                                    <li>Published On May 19, 2026 at 01:37 PM IST</li>\n                                    <!-- <li class=\"desktop-view\">2 min read</li> -->\n                                </ul>\n                            \n                                        \n\n                    \n\n                    <!-- Comment Section -->\n                                            \n                                        <!-- Comment Section -->\n\n                    \n                      \n    \n            <p>\n                </p><h2>Join the community of 2M+ industry professionals. </h2>   \n                <h3>Subscribe to Newsletter to get latest insights &amp; analysis in your inbox.</h3>\n            <p></p>\n\n            <!-- <figure class=\"top-newsletter-subs__icon-nl\" role=\"presentation\" aria-label=\"Newsletter icon\">\n                <img loading=\"lazy\" src=\"https://st.etb2bimg.com/Themes/Release/theme4/images/icons/icon-newsletter.svg\" alt=\"Newsletter icon\" width=\"55\" height=\"55\">\n            </figure> -->\n        \n            \n                \n                    <h2>All about ETHealthworld industry right on your smartphone! </h2>\n                    <ul>\n                        <li><a href=\"/app\" target=\"_blank\" rel=\"noopener noreferrer\">Download the ETHealthworld App</a> and get the Realtime updates and Save your favourite articles.</li>\n                    </ul>\n                                            <!-- <div class=\"app-store-container desktop-view\">\n                            <a href=\"/app\" title=\"\" aria-label=\"Play Store\">\n                                <img loading=\"lazy\" width=\"20\" height=\"20\" src=\"https://st.etb2bimg.com/Themes/Release/theme4/images/icons/icon-g-play.png\" alt=\"\" />\n                            </a>\n                            <a href=\"/app\" title=\"App Store\">\n                                <img loading=\"lazy\" width=\"20\" height=\"20\" src=\"https://st.etb2bimg.com/Themes/Release/theme4/images/icons/icon-app-store.png\" alt=\"\" />\n                            </a>\n                        </div>    -->\n                         \n                \n                                    <figure>\n                        <!-- <i></i>\n                        <span class=\"scan-text\">Scan to download App</span> -->\n                        <img src=\"https://st.etb2bimg.com/Themes/Release/theme4/images/bar-codes/health_barcode.png?mod=3298\" alt=\"\">                        \n                        <!-- <span class=\"border-bottom\"></span> -->\n                    </figure>\n                            \n       \n\n\n                    \n                \n            "
}
