{
  "id": "2026-05-10-quadria-arm-to-back-patient-monitoring-platform-lifesigns",
  "issueKey": "2026-05-10",
  "segment": "pharma",
  "title": "Quadria-arm to back patient monitoring platform LifeSigns",
  "summary": "The fresh capital will be deployed in expanding the Chennai-based startup's international footprint and strengthening its AI-led technology stack through selective integrations.",
  "source": "ET Healthworld",
  "sourceHost": "health.economictimes.indiatimes.com",
  "region": "India",
  "country": "India",
  "publishedAt": "2026-05-11T09:36:49.000Z",
  "publishedLabel": "May 11, 2026",
  "category": "Industry Update",
  "image": "https://etimg.etb2bimg.com/thumb/msid-131010068,imgsize-5154,width-1200,height=627,overlay-ethealth,resizemode-75/health-it/quadria-arm-to-back-patient-monitoring-platform-lifesigns.jpg",
  "thbAction": "Position THB's pharma CRM and omnichannel HCP engagement workflows to support launch planning, KAM orchestration, and compliant follow-up across India and the Middle East.",
  "justIn": true,
  "originalUrl": "https://health.economictimes.indiatimes.com/news/health-it/quadria-arm-to-back-patient-monitoring-platform-lifesigns/131010068",
  "canonicalUrl": "https://health.economictimes.indiatimes.com/news/health-it/quadria-arm-to-back-patient-monitoring-platform-lifesigns/131010068",
  "contentHtml": "\n                                    \n\n                                                                            <p><img src=\"https://health.economictimes.indiatimes.com/Themes/Release/theme4/images/icons/et-default-user.svg\" alt=\"Online Bureau\">\n                                            \n                                        </p>\n                                                                        \n                                                                                    <ul>\n                                                                                                    <li>\n                                                                                                                    <a>Online Bureau</a>\n\n                                                                                                                                                                                                                                        \n                                                                                                            </li>\n                                                                                                                                                    <li><a href=\"/agency/88675629/ETHealthWorld\" target=\"_blank\" rel=\"noopener noreferrer\">ETHealthWorld</a></li>\n                                                                                            </ul>\n                                                                                <ul>\n                                                                                            <li>Published On May 11, 2026 at 03:06 PM IST</li>\n                                                                                                                                </ul>\n                                    \n                                                                            \n                                                                        \n                                \n                                \n\n                    <!-- Display video article in news article for the custom next story -->\n                    \n                    <!-- Modifying the body placing embeds,promoslots,related etc.-->\n                                        <figure><img src=\"/images/default.jpg\" alt=\"\"></figure><p>New Delhi: <a href=\"/tag/quadria+group\" target=\"_blank\" rel=\"noopener noreferrer\">Quadria Group</a>’s healthcare venture arm, <a href=\"/tag/healthquad\" target=\"_blank\" rel=\"noopener noreferrer\">HealthQuad</a> has has announced to invest an disclosed sum in <a href=\"/tag/ai-driven+patient+monitoring\" target=\"_blank\" rel=\"noopener noreferrer\">AI-driven patient monitoring</a> platform <a href=\"/tag/lifesigns\" target=\"_blank\" rel=\"noopener noreferrer\">LifeSigns</a>. The fresh capital will be deployed in expanding the Chennai-based startup's international footprint across Southeast Asia and the GCC region and strengthening its AI-led technology stack through selective integrations.</p><!-- PROMOSLOT_M --><p>Founded in 2019, <a href=\"/tag/lifesigns\" target=\"_blank\" rel=\"noopener noreferrer\">LifeSigns</a> is a US FDA-approved continuous patient monitoring platform, which integrates medical grade wearable and cloud dashboard with a <a href=\"/tag/predictive+ai+engine\" target=\"_blank\" rel=\"noopener noreferrer\">predictive AI engine</a> to provide safety alters by monitoring, heart rate, respiration, temperature, blood pressure, and oxygen saturation. </p>\n                            <p>Advt\n                            </p>\n\n                              \n                                                         \n                        <p>It flags early signs of deterioration to enable timely clinical intervention and is stated to be adopted by 50 facilities across tier 2 cities. </p><!-- PROMOSLOT_M --><p>So far the platform has monitored over 325,000 patients and generated more than 87,000 alerts. According to a company release the platform has helped to reduced code blue incidents by 90 per cent, and lowered ICU readmissions by nearly 78 per cent. Quadria's $350 million <a href=\"/tag/healthquad\" target=\"_blank\" rel=\"noopener noreferrer\">HealthQuad</a> Fund, backs new-age healthcare business models with global relevance. </p><!-- PROMOSLOT_M --><p>“LifeSigns is building that layer to detect deterioration early and enable timely intervention which can significantly improve outcomes and reduce healthcare costs at scale. This is a globally relevant model and where the next wave of healthcare will be built,” said Rahul Agarwal, Partner, HealthQuad.                    </p><!-- Category Most Read Placement -->\n                                                                    \n                                                                \n                                <ul>\n                                                                            <!-- <li>By <span>Online Bureau</span>,</li> -->\n                                    \n\n                                                                            <li>By\n                                                                                            <a>Online Bureau</a>\n\n                                                                                                                                                                                        , \n                                                                                    </li>\n                                                                        <li><a href=\"/agency/88675629/ETHealthWorld\" target=\"_blank\" rel=\"noopener noreferrer\">ETHealthWorld</a></li>\n                                </ul>\n                                <ul>\n                                    <!-- <li> Updated On May 11, 2026 at 03:06 PM IST</li> -->\n                                    <li>Published On May 11, 2026 at 03:06 PM IST</li>\n                                    <!-- <li class=\"desktop-view\">1 min read</li> -->\n                                </ul>\n                            \n                                        \n\n                    \n\n                    <!-- Comment Section -->\n                                            \n                                        <!-- Comment Section -->\n\n                    \n                      \n    \n            <p>\n                </p><h2>Join the community of 2M+ industry professionals. </h2>   \n                <h3>Subscribe to Newsletter to get latest insights &amp; analysis in your inbox.</h3>\n            <p></p>\n\n            <!-- <figure class=\"top-newsletter-subs__icon-nl\" role=\"presentation\" aria-label=\"Newsletter icon\">\n                <img loading=\"lazy\" src=\"https://st.etb2bimg.com/Themes/Release/theme4/images/icons/icon-newsletter.svg\" alt=\"Newsletter icon\" width=\"55\" height=\"55\">\n            </figure> -->\n        \n            \n                \n                    <h2>All about ETHealthworld industry right on your smartphone! </h2>\n                    <ul>\n                        <li><a href=\"/app\" target=\"_blank\" rel=\"noopener noreferrer\">Download the ETHealthworld App</a> and get the Realtime updates and Save your favourite articles.</li>\n                    </ul>\n                                            <!-- <div class=\"app-store-container desktop-view\">\n                            <a href=\"/app\" title=\"\" aria-label=\"Play Store\">\n                                <img loading=\"lazy\" width=\"20\" height=\"20\" src=\"https://st.etb2bimg.com/Themes/Release/theme4/images/icons/icon-g-play.png\" alt=\"\" />\n                            </a>\n                            <a href=\"/app\" title=\"App Store\">\n                                <img loading=\"lazy\" width=\"20\" height=\"20\" src=\"https://st.etb2bimg.com/Themes/Release/theme4/images/icons/icon-app-store.png\" alt=\"\" />\n                            </a>\n                        </div>    -->\n                         \n                \n                                    <figure>\n                        <!-- <i></i>\n                        <span class=\"scan-text\">Scan to download App</span> -->\n                        <img src=\"https://st.etb2bimg.com/Themes/Release/theme4/images/bar-codes/health_barcode.png?mod=3289\" alt=\"\">                        \n                        <!-- <span class=\"border-bottom\"></span> -->\n                    </figure>\n                            \n       \n\n\n                    \n                \n            "
}
